{
  "id": "VogtMinimal",
  "description": "Encodes EVA using Derek Vogt's phonology.",
  "changes": "",

  "patterns": [
    {
      // ^w^
      "input": "a",
      "repr": "w",
      "features": [ "-Cons", "+Son", "-Syll", "+Labial", "+Round", "-Cor", "+Dorsal", "+High", "-Low", "-Back", "-Tense", "-Phar", "+Voice", "-SG", "-CG", "+Cont", "-Strident", "-Lateral", "-DelRel", "-Nasal" ]
    },
    {
      // ^h^
      "input": "ch",
      "repr": "h",
      "features": [ "-Cons", "-Son", "-Syll", "-Labial", "-Cor", "-Dorsal", "-Phar", "-Voice", "+SG", "-CG", "+Cont", "-Strident", "-Lateral", "-DelRel", "-Nasal" ]
    },
    {
      // ^h^
      "input": "c",
      "repr": "h",
      "features": [ "-Cons", "-Son", "-Syll", "-Labial", "-Cor", "-Dorsal", "-Phar", "-Voice", "+SG", "-CG", "+Cont", "-Strident", "-Lateral", "-DelRel", "-Nasal" ]
    },
    {
      // ^h^
      "input": "h",
      "repr": "h",
      "features": [ "-Cons", "-Son", "-Syll", "-Labial", "-Cor", "-Dorsal", "-Phar", "-Voice", "+SG", "-CG", "+Cont", "-Strident", "-Lateral", "-DelRel", "-Nasal" ]
    },
    {
      // ^t^
      "input": "d",
      "repr": "t",
      "features": [ "+Cons", "-Son", "-Syll", "-Labial", "+Cor", "+Ant", "-Dist", "-Dorsal", "-Phar", "-Voice", "-SG", "-CG", "-Cont", "-Strident", "-Lateral", "-DelRel", "-Nasal" ]
    },
    {
      // ^o^
      "input": "e",
      "repr": "o",
      "features": [ "-Cons", "+Son", "+Syll", "+Labial", "+Round", "-Cor", "+Dorsal", "-High", "-Low", "+Back", "+Tense", "+Phar", "+ATR", "+Voice", "-SG", "-CG", "+Cont", "-Strident", "-Lateral", "-DelRel", "-Nasal" ]
    },
    {
      // ^p^
      "input": "f",
      "repr": "p",
      "features": [ "+Cons", "-Son", "-Syll", "+Labial", "-Round", "-Cor", "-Dorsal", "-Phar", "-Voice", "-SG", "-CG", "-Cont", "-Strident", "-Lateral", "-DelRel", "-Nasal" ]
    },
    {
      // ^f^
      "input": "cfh",
      "repr": "f",
      "features": [ "+Cons", "-Son", "-Syll", "+Labial", "-Round", "-Cor", "-Dorsal", "-Phar", "-Voice", "-SG", "-CG", "+Cont", "+Strident", "-Lateral", "-DelRel", "-Nasal" ]
    },
    {
      // ^f^
      "input": "cFh",
      "repr": "f",
      "features": [ "+Cons", "-Son", "-Syll", "+Labial", "-Round", "-Cor", "-Dorsal", "-Phar", "-Voice", "-SG", "-CG", "+Cont", "+Strident", "-Lateral", "-DelRel", "-Nasal" ]
    },
    {
      // ^r^
      "input": "g",
      "repr": "r",
      "features": [ "+Cons", "+Son", "-Syll", "-Labial", "+Cor", "+Ant", "-Dist", "-Dorsal", "-Phar", "+Voice", "-SG", "-CG", "+Cont", "-Strident", "-Lateral", "-DelRel", "-Nasal" ]
    },
    {
      // ^k^
      "input": "k",
      "repr": "k",
      "features": [ "+Cons", "-Son", "-Syll", "-Labial", "-Cor", "+Dorsal", "+High", "-Low", "+Back", "-Tense", "-Phar", "-Voice", "-SG", "-CG", "-Cont", "-Strident", "-Lateral", "-DelRel", "-Nasal" ]
    },
    {
      // ^č^
      "input": "cKh",
      "repr": "č",
      "features": [ "+Cons", "-Son", "-Syll", "-Labial", "+Cor", "-Ant", "+Dist", "+Dorsal", "+High", "-Low", "-Back", "-Tense", "-Phar", "-Voice", "-SG", "-CG", "+Strident", "-Lateral", "+DelRel", "-Nasal" ]
    },
    {
      // ^č^
      "input": "ckh",
      "repr": "č",
      "features": [ "+Cons", "-Son", "-Syll", "-Labial", "+Cor", "-Ant", "+Dist", "+Dorsal", "+High", "-Low", "-Back", "-Tense", "-Phar", "-Voice", "-SG", "-CG", "+Strident", "-Lateral", "+DelRel", "-Nasal" ]
    },
    {
      // ^ʃ^
      "input": "l",
      "repr": "ʃ",
      "features": [ "+Cons", "-Son", "-Syll", "-Labial", "+Cor", "-Ant", "+Dist", "-Dorsal", "-Phar", "-Voice", "-SG", "-CG", "+Cont", "-Strident", "-Lateral", "-DelRel", "-Nasal" ]
    },
    {
      // ^r^
      "input": "m",
      "repr": "r",
      "features": [ "+Cons", "+Son", "-Syll", "-Labial", "+Cor", "+Ant", "-Dist", "-Dorsal", "-Phar", "+Voice", "-SG", "-CG", "+Cont", "-Strident", "-Lateral", "-DelRel", "-Nasal" ]
    },
    {
      // ^æ^
      "input": "o",
      "repr": "æ",
      "features": [ "-Cons", "+Son", "+Syll", "+Labial", "-Round", "-Cor", "+Dorsal", "-High", "+Low", "-Back", "+Tense", "+Phar", "-ATR", "+Voice", "-SG", "-CG", "+Cont", "-Strident", "-Lateral", "-DelRel", "-Nasal" ]
    },
    {
      // ^b^
      "input": "p",
      "repr": "b",
      "features": [ "+Cons", "-Son", "-Syll", "+Labial", "-Round", "-Cor", "-Dorsal", "-Phar", "+Voice", "-SG", "-CG", "-Cont", "-Strident", "-Lateral", "-DelRel", "-Nasal" ]
    },
    {
      // ^v^
      "input": "cPh",
      "repr": "v",
      "features": [ "+Cons", "-Son", "-Syll", "+Labial", "-Round", "-Cor", "-Dorsal", "-Phar", "+Voice", "-SG", "-CG", "+Cont", "+Strident", "-Lateral", "-DelRel", "-Nasal" ]
    },
    {
      // ^v^
      "input": "cph",
      "repr": "v",
      "features": [ "+Cons", "-Son", "-Syll", "+Labial", "-Round", "-Cor", "-Dorsal", "-Phar", "+Voice", "-SG", "-CG", "+Cont", "+Strident", "-Lateral", "-DelRel", "-Nasal" ]
    },
    {
      // ^r^
      "input": "r",
      "repr": "r",
      "features": [ "+Cons", "+Son", "-Syll", "-Labial", "+Cor", "+Ant", "-Dist", "-Dorsal", "-Phar", "+Voice", "-SG", "-CG", "+Cont", "-Strident", "-Lateral", "-DelRel", "-Nasal" ]
    },
    {
      // ^s^
      "input": "s",
      "repr": "s",
      "features": [ "+Cons", "-Son", "-Syll", "-Labial", "+Cor", "+Ant", "-Dist", "-Dorsal", "-Phar", "-Voice", "-SG", "-CG", "+Cont", "+Strident", "-Lateral", "-DelRel", "-Nasal" ]
    },
    {
      // ^x^
      "input": "Sh",
      "repr": "x",
      "features": [ "+Cons", "-Son", "-Syll", "-Labial", "-Cor", "+Dorsal", "+High", "-Low", "+Back", "-Tense", "-Phar", "-Voice", "-SG", "-CG", "+Cont", "-Strident", "-Lateral", "-DelRel", "-Nasal" ]
    },
    {
      // ^x^
      "input": "sh",
      "repr": "x",
      "features": [ "+Cons", "-Son", "-Syll", "-Labial", "-Cor", "+Dorsal", "+High", "-Low", "+Back", "-Tense", "-Phar", "-Voice", "-SG", "-CG", "+Cont", "-Strident", "-Lateral", "-DelRel", "-Nasal" ]
    },
    {
      // ^g^
      "input": "t",
      "repr": "g",
      "features": [ "+Cons", "-Son", "-Syll", "-Labial", "-Cor", "+Dorsal", "+High", "-Low", "+Back", "-Tense", "-Phar", "+Voice", "-SG", "-CG", "-Cont", "-Strident", "-Lateral", "-DelRel", "-Nasal" ]
    },
    {
      // ^ǧ^
      "input": "cTh",
      "repr": "ǧ",
      "features": [ "+Cons", "-Son", "-Syll", "-Labial", "+Cor", "-Ant", "+Dist", "+Dorsal", "+High", "-Low", "-Back", "-Tense", "-Phar", "+Voice", "-SG", "-CG", "+Strident", "-Lateral", "+DelRel", "-Nasal" ]
    },
    {
      // ^ǧ^
      "input": "cth",
      "repr": "ǧ",
      "features": [ "+Cons", "-Son", "-Syll", "-Labial", "+Cor", "-Ant", "+Dist", "+Dorsal", "+High", "-Low", "-Back", "-Tense", "-Phar", "+Voice", "-SG", "-CG", "+Strident", "-Lateral", "+DelRel", "-Nasal" ]
    },
    {
      // ^n^
      "input": "y",
      "repr": "n",
      "features": [ "+Cons", "+Son", "-Syll", "-Labial", "-Dorsal", "-Phar", "+Voice", "-CG", "-Cont", "-Strident", "-Lateral", "-DelRel", "+Nasal" ]
    }
  ]
}
